stereotech_cloud_commons/__init__.py
stereotech_cloud_commons/app.py
stereotech_cloud_commons/confighelper.py
stereotech_cloud_commons/eventloop.py
stereotech_cloud_commons/stereotech_cloud.py
stereotech_cloud_commons/utils.py
stereotech_cloud_commons/websockets.py
stereotech_cloud_commons/components/__init__.py
stereotech_cloud_commons/components/authorization.py
stereotech_cloud_commons/components/mongo_database.py
stereotech_cloud_commons/components/mq.py
stereotech_cloud_commons/components/notification.py
stereotech_cloud_commons/components/roles.py
stereotech_cloud_commons/components/settings.py
stereotech_cloud_commons/components/storage.py
stereotech_cloud_commons/components/teams.py
tests/__init__.py
tests/test_notification.py
stereotech_cloud_commons-1.2.13.dist-info/LICENSE
stereotech_cloud_commons-1.2.13.dist-info/METADATA
stereotech_cloud_commons-1.2.13.dist-info/WHEEL
stereotech_cloud_commons-1.2.13.dist-info/top_level.txt
stereotech_cloud_commons-1.2.13.dist-info/RECORD
