Metadata-Version: 2.1
Name: stereotech-cloud-commons
Version: 1.2.13
Summary: Common components for Stereotech Cloud microservices
Author-email: Stereotech Dev Team <dev@5dtech.pro>
License: GNU GENERAL PUBLIC LICENSE
Project-URL: Homepage, https://github.com/stereotech/stereotech-cloud-commons
Project-URL: Bug Tracker, https://github.com/stereotech/stereotech-cloud-commons/issues
Classifier: Programming Language :: Python :: 3
Classifier: License :: OSI Approved :: MIT License
Classifier: Operating System :: OS Independent
Requires-Python: >=3.7
License-File: LICENSE
Requires-Dist: tornado ==6.1.0
Requires-Dist: pymongo ==4.2.0
Requires-Dist: Pillow ==9.3.0
Requires-Dist: mongoengine ==0.27.0
Requires-Dist: pika ==1.3.2
Requires-Dist: blinker ==1.7.0
